lorenz_attractor/__init__.py
lorenz_attractor/cli.py
lorenz_attractor/analysis/__init__.py
lorenz_attractor/core/__init__.py
lorenz_attractor/core/lorenz.py
lorenz_attractor/core/parameters.py
lorenz_attractor/core/simulator.py
lorenz_attractor/export/__init__.py
lorenz_attractor/export/data.py
lorenz_attractor/export/image.py
lorenz_attractor/export/video.py
lorenz_attractor/integration/__init__.py
lorenz_attractor/integration/integrators.py
lorenz_attractor/utils/__init__.py
lorenz_attractor/visualization/__init__.py
lorenz_attractor/visualization/interactive.py
lorenz_attractor/visualization/opengl_renderer.py
lorenz_attractor/visualization/plotter.py
lorenz_attractor/visualization/realtime.py
lorenz_attractor/web/__init__.py
lorenz_attractor/web/app.py
lorenz_attractor-2.0.0.dist-info/METADATA
lorenz_attractor-2.0.0.dist-info/WHEEL
lorenz_attractor-2.0.0.dist-info/entry_points.txt
lorenz_attractor-2.0.0.dist-info/top_level.txt
lorenz_attractor-2.0.0.dist-info/RECORD
