Metadata-Version: 2.4
Name: lorenz-attractor
Version: 2.0.0
Summary: Professional-grade Lorenz attractor simulation suite
Author-email: Jose Solis Rosales <josesolisrosales@linux.com>
License: MIT
Project-URL: Homepage, https://github.com/josesolisrosales/lorenz-attractor
Project-URL: Repository, https://github.com/josesolisrosales/lorenz-attractor
Project-URL: Issues, https://github.com/josesolisrosales/lorenz-attractor/issues
Classifier: Development Status :: 5 - Production/Stable
Classifier: Intended Audience :: Science/Research
Classifier: License :: OSI Approved :: MIT License
Classifier: Operating System :: OS Independent
Classifier: Programming Language :: Python :: 3
Classifier: Programming Language :: Python :: 3.8
Classifier: Programming Language :: Python :: 3.9
Classifier: Programming Language :: Python :: 3.10
Classifier: Programming Language :: Python :: 3.11
Classifier: Topic :: Scientific/Engineering :: Mathematics
Classifier: Topic :: Scientific/Engineering :: Physics
Classifier: Topic :: Scientific/Engineering :: Visualization
Requires-Python: >=3.8
Requires-Dist: numpy>=1.21.0
Requires-Dist: matplotlib>=3.5.0
Requires-Dist: scipy>=1.8.0
Requires-Dist: PyOpenGL>=3.1.0
Requires-Dist: pygame>=2.1.0
Requires-Dist: flask>=2.0.0
Requires-Dist: plotly>=5.0.0
Requires-Dist: opencv-python>=4.5.0
Requires-Dist: numba>=0.56.0
Requires-Dist: pillow>=9.0.0
Provides-Extra: dev
Requires-Dist: pytest>=7.0.0; extra == "dev"
Requires-Dist: black>=23.0.0; extra == "dev"
Requires-Dist: flake8>=6.0.0; extra == "dev"
Provides-Extra: gpu
Requires-Dist: cupy>=12.0.0; extra == "gpu"
Requires-Dist: cuda-python>=12.0.0; extra == "gpu"
